<?xml version="1.0" encoding="UTF-8"?>
<databaseChangeLog
        xmlns="http://www.liquibase.org/xml/ns/dbchangelog"
        xmlns:xsi="http://www.w3.org/2001/XMLSchema-instance"
        xsi:schemaLocation="http://www.liquibase.org/xml/ns/dbchangelog
        http://www.liquibase.org/xml/ns/dbchangelog/dbchangelog-3.1.xsd">
    <changeSet id="insert-into-author" author="akiselev">
        <insert tableName="author">
            <column name="first_name" value="Alexey"></column>
            <column name="last_name" value="Kiselev"></column>
        </insert>
        <insert tableName="author">
            <column name="first_name" value="Evgeniy"></column>
            <column name="last_name" value="Kiselev"></column>
        </insert>
    </changeSet>
</databaseChangeLog>